horsejax/__init__.py
horsejax/api.json
horsejax/api.py
twisted/plugins/horsejax.py
horsejax-0.1.2.dist-info/top_level.txt
horsejax-0.1.2.dist-info/METADATA
horsejax-0.1.2.dist-info/DESCRIPTION.rst
horsejax-0.1.2.dist-info/pydist.json
horsejax-0.1.2.dist-info/WHEEL
horsejax-0.1.2.dist-info/RECORD
