Metadata-Version: 2.0
Name: horsejax
Version: 0.1.2
Summary: Secure password generator via not so secure JSON.
Home-page: https://github.com/hawkowl/horsejax/
Author: HawkOwl
Author-email: hawkowl@atleastfornow.net
License: MIT
Platform: UNKNOWN
Classifier: Programming Language :: Python :: 2.7
Requires-Dist: horsephrase
Requires-Dist: haddock
